django_downloadview/__init__.py
django_downloadview/api.py
django_downloadview/decorators.py
django_downloadview/exceptions.py
django_downloadview/files.py
django_downloadview/io.py
django_downloadview/middlewares.py
django_downloadview/response.py
django_downloadview/shortcuts.py
django_downloadview/storage.py
django_downloadview/test.py
django_downloadview/utils.py
django_downloadview/apache/__init__.py
django_downloadview/apache/decorators.py
django_downloadview/apache/middlewares.py
django_downloadview/apache/response.py
django_downloadview/apache/tests.py
django_downloadview/lighttpd/__init__.py
django_downloadview/lighttpd/decorators.py
django_downloadview/lighttpd/middlewares.py
django_downloadview/lighttpd/response.py
django_downloadview/lighttpd/tests.py
django_downloadview/nginx/__init__.py
django_downloadview/nginx/decorators.py
django_downloadview/nginx/middlewares.py
django_downloadview/nginx/response.py
django_downloadview/nginx/settings.py
django_downloadview/nginx/tests.py
django_downloadview/views/__init__.py
django_downloadview/views/base.py
django_downloadview/views/http.py
django_downloadview/views/object.py
django_downloadview/views/path.py
django_downloadview/views/storage.py
django_downloadview/views/virtual.py
django_downloadview-2.4.0.dist-info/AUTHORS
django_downloadview-2.4.0.dist-info/LICENSE
django_downloadview-2.4.0.dist-info/METADATA
django_downloadview-2.4.0.dist-info/WHEEL
django_downloadview-2.4.0.dist-info/top_level.txt
django_downloadview-2.4.0.dist-info/RECORD
