Metadata-Version: 2.1
Name: django-downloadview
Version: 2.4.0
Summary: Serve files with Django and reverse-proxies.
Home-page: https://django-downloadview.readthedocs.io/
Author: Benoît Bryon
Author-email: benoit@marmelune.net
License: BSD
Keywords: file stream download FileField ImageField x-accel x-accel-redirect x-sendfile sendfile mod_xsendfile offload
Classifier: Development Status :: 5 - Production/Stable
Classifier: License :: OSI Approved :: BSD License
Classifier: Programming Language :: Python :: 3 :: Only
Classifier: Programming Language :: Python :: 3.8
Classifier: Programming Language :: Python :: 3.9
Classifier: Programming Language :: Python :: 3.10
Classifier: Programming Language :: Python :: 3.11
Classifier: Programming Language :: Python :: 3.12
Classifier: Framework :: Django
Classifier: Framework :: Django :: 4.2
Classifier: Framework :: Django :: 5.0
Requires-Python: >=3.8
License-File: LICENSE
License-File: AUTHORS
Requires-Dist: Django>=4.2
Requires-Dist: requests
Provides-Extra: test
Requires-Dist: tox; extra == "test"
